entropy_pooling/__init__.py
entropy_pooling/entropy_pooling.py
entropy_pooling-1.0.8.dist-info/METADATA
entropy_pooling-1.0.8.dist-info/WHEEL
entropy_pooling-1.0.8.dist-info/LICENSE
entropy_pooling-1.0.8.dist-info/RECORD
