Metadata-Version: 2.1
Name: entropy-pooling
Version: 1.0.8
Summary: Entropy Pooling in Python with a BSD 3-Clause license.
Home-page: https://fortitudo.tech
License: BSD-3-Clause
Keywords: Entropy Pooling,Quantitative Finance,Monte Carlo,Stress-Testing,CVaR
Author: Fortitudo Technologies
Author-email: software@fortitudo.tech
Requires-Python: >=3.9,<3.13
Classifier: Intended Audience :: Education
Classifier: Intended Audience :: Financial and Insurance Industry
Classifier: Intended Audience :: Science/Research
Classifier: License :: OSI Approved :: BSD License
Classifier: Programming Language :: Python :: 3
Classifier: Programming Language :: Python :: 3.9
Classifier: Programming Language :: Python :: 3.10
Classifier: Programming Language :: Python :: 3.11
Classifier: Programming Language :: Python :: 3.10
Classifier: Programming Language :: Python :: 3.11
Classifier: Programming Language :: Python :: 3.12
Classifier: Programming Language :: Python :: 3.9
Classifier: Topic :: Office/Business :: Financial
Classifier: Topic :: Office/Business :: Financial :: Investment
Classifier: Topic :: Scientific/Engineering :: Mathematics
Requires-Dist: scipy (>=1.10,<2.0)
Project-URL: Documentation, https://os.fortitudo.tech
Project-URL: Issues, https://github.com/fortitudo-tech/entropy-pooling/issues
Project-URL: Repository, https://github.com/fortitudo-tech/entropy-pooling
